Blauwal3_Bioinformatics-4.8.3-py3.10-nspkg.pth
orangecontrib/bioinformatics/__init__.py
orangecontrib/bioinformatics/i18n_config.py
orangecontrib/bioinformatics/annotation/__init__.py
orangecontrib/bioinformatics/annotation/annotate_projection.py
orangecontrib/bioinformatics/annotation/annotate_samples.py
orangecontrib/bioinformatics/cluster_analysis/__init__.py
orangecontrib/bioinformatics/dicty/__init__.py
orangecontrib/bioinformatics/dicty/phenotypes.py
orangecontrib/bioinformatics/geneset/__init__.py
orangecontrib/bioinformatics/geneset/utils.py
orangecontrib/bioinformatics/geo/__init__.py
orangecontrib/bioinformatics/geo/dataset.py
orangecontrib/bioinformatics/go/__init__.py
orangecontrib/bioinformatics/go/config.py
orangecontrib/bioinformatics/kegg/__init__.py
orangecontrib/bioinformatics/kegg/api.py
orangecontrib/bioinformatics/kegg/brite.py
orangecontrib/bioinformatics/kegg/caching.py
orangecontrib/bioinformatics/kegg/conf.py
orangecontrib/bioinformatics/kegg/databases.py
orangecontrib/bioinformatics/kegg/pathway.py
orangecontrib/bioinformatics/kegg/service.py
orangecontrib/bioinformatics/kegg/types.py
orangecontrib/bioinformatics/kegg/entry/__init__.py
orangecontrib/bioinformatics/kegg/entry/fields.py
orangecontrib/bioinformatics/kegg/entry/parser.py
orangecontrib/bioinformatics/locale/bioinformatics.de.yml
orangecontrib/bioinformatics/locale/bioinformatics.en.yml
orangecontrib/bioinformatics/locale/bioinformatics.zh.yml
orangecontrib/bioinformatics/ncbi/__init__.py
orangecontrib/bioinformatics/ncbi/gene/__init__.py
orangecontrib/bioinformatics/ncbi/gene/config.py
orangecontrib/bioinformatics/ncbi/homologene/__init__.py
orangecontrib/bioinformatics/ncbi/taxonomy/__init__.py
orangecontrib/bioinformatics/ncbi/taxonomy/utils.py
orangecontrib/bioinformatics/preprocess/__init__.py
orangecontrib/bioinformatics/preprocess/normalize.py
orangecontrib/bioinformatics/resolwe/__init__.py
orangecontrib/bioinformatics/resolwe/genapi.py
Blauwal3_Bioinformatics-4.8.3.dist-info/LICENSE
Blauwal3_Bioinformatics-4.8.3.dist-info/METADATA
Blauwal3_Bioinformatics-4.8.3.dist-info/WHEEL
Blauwal3_Bioinformatics-4.8.3.dist-info/entry_points.txt
Blauwal3_Bioinformatics-4.8.3.dist-info/namespace_packages.txt
Blauwal3_Bioinformatics-4.8.3.dist-info/top_level.txt
Blauwal3_Bioinformatics-4.8.3.dist-info/RECORD
