Metadata-Version: 2.1
Name: Blauwal3-Bioinformatics
Version: 4.8.3
Summary: 用于数据挖掘的蓝鲸生物信息学附加组件。
Home-page: https://github.com/biolab/orange3-bioinformatics
Author: 大圣实验楼
Author-email: dashenglab@163.com
Maintainer: Jaka Kokosar
License: GPL3+
Project-URL: Bug Tracker, https://github.com/biolab/orange3-bioinformatics/issues
Project-URL: Documentation, https://orange3-bioinformatics.readthedocs.io/en/latest/
Project-URL: Source Code, https://github.com/biolab/orange3-bioinformatics/
Keywords: 'orange3 add-on'
Classifier: License :: OSI Approved :: GNU General Public License v3 or later (GPLv3+)
Classifier: Topic :: Scientific/Engineering :: Artificial Intelligence
Classifier: Topic :: Scientific/Engineering :: Visualization
Classifier: Topic :: Scientific/Engineering :: Bio-Informatics
Classifier: Topic :: Software Development :: Libraries :: Python Modules
Classifier: Intended Audience :: Education
Classifier: Intended Audience :: Science/Research
Classifier: Intended Audience :: Developers
Classifier: Development Status :: 1 - Planning
Classifier: Programming Language :: Python :: 3 :: Only
Classifier: Operating System :: OS Independent
Requires-Python: >=3.6
License-File: LICENSE
Requires-Dist: Blauwal3>=3.38.0
Requires-Dist: Blauwal3-widget-base
Requires-Dist: scipy>=1.5.0
Requires-Dist: pyclipper>=1.2.0
Requires-Dist: point-annotator~=2.0
Requires-Dist: requests
Requires-Dist: requests-cache>=0.8.0
Requires-Dist: resdk>=20.0.0
Requires-Dist: genesis-pyapi
Requires-Dist: single-sample-gsea>=0.2.0
Requires-Dist: numpy
Requires-Dist: serverfiles
Provides-Extra: doc
Requires-Dist: sphinx; extra == "doc"
Requires-Dist: recommonmark; extra == "doc"
Requires-Dist: sphinx-rtd-theme; extra == "doc"
Requires-Dist: docutils<0.17; extra == "doc"
Provides-Extra: test
Requires-Dist: flake8; extra == "test"
Requires-Dist: flake8-comprehensions; extra == "test"
Requires-Dist: flake8-black; extra == "test"
Requires-Dist: pep8-naming; extra == "test"
Requires-Dist: isort; extra == "test"
Requires-Dist: pre-commit; extra == "test"
Requires-Dist: pytest; extra == "test"
Requires-Dist: coverage; extra == "test"
Requires-Dist: codecov; extra == "test"
